quakupy/__init__.py
quakupy/_base_client.py
quakupy/_client.py
quakupy/_compat.py
quakupy/_constants.py
quakupy/_exceptions.py
quakupy/_files.py
quakupy/_models.py
quakupy/_qs.py
quakupy/_resource.py
quakupy/_response.py
quakupy/_streaming.py
quakupy/_types.py
quakupy/_version.py
quakupy/py.typed
quakupy/_utils/__init__.py
quakupy/_utils/_logs.py
quakupy/_utils/_proxy.py
quakupy/_utils/_reflection.py
quakupy/_utils/_resources_proxy.py
quakupy/_utils/_streams.py
quakupy/_utils/_sync.py
quakupy/_utils/_transform.py
quakupy/_utils/_typing.py
quakupy/_utils/_utils.py
quakupy/lib/.keep
quakupy/resources/__init__.py
quakupy/resources/agent.py
quakupy/resources/dataset.py
quakupy/resources/management.py
quakupy/resources/source.py
quakupy/resources/history/__init__.py
quakupy/resources/history/flow.py
quakupy/resources/history/history.py
quakupy/resources/history/quark.py
quakupy/resources/registry/__init__.py
quakupy/resources/registry/lattice.py
quakupy/resources/registry/registry.py
quakupy/resources/registry/quark/__init__.py
quakupy/resources/registry/quark/quark.py
quakupy/resources/registry/quark/ai/__init__.py
quakupy/resources/registry/quark/ai/ai.py
quakupy/resources/registry/quark/ai/openai_completion_base.py
quakupy/resources/registry/quark/ai/openai_embeddings.py
quakupy/resources/registry/quark/databases/__init__.py
quakupy/resources/registry/quark/databases/databases.py
quakupy/resources/registry/quark/databases/snowflake_read.py
quakupy/resources/registry/quark/extractor/__init__.py
quakupy/resources/registry/quark/extractor/docling_extractor.py
quakupy/resources/registry/quark/extractor/extractor.py
quakupy/resources/registry/quark/files/__init__.py
quakupy/resources/registry/quark/files/files.py
quakupy/resources/registry/quark/files/opendal.py
quakupy/resources/registry/quark/files/s3_read_csv.py
quakupy/resources/registry/quark/files/s3_read_files_binary.py
quakupy/resources/registry/quark/transformer/__init__.py
quakupy-0.1.0a8.dist-info/METADATA
quakupy-0.1.0a8.dist-info/WHEEL
quakupy-0.1.0a8.dist-info/licenses/LICENSE
quakupy-0.1.0a8.dist-info/RECORD
